Metadata-Version: 1.0
Name: maestroclient
Version: 0.1
Summary: Client for accessing Maestro API
Home-page: UNKNOWN
Author: Sam Dela Cruz
Author-email: sammydc@gmail.com
License: MIT
Platform: UNKNOWN
